odoo/addons/beesdoo_stock_coverage/README.rst
odoo/addons/beesdoo_stock_coverage/__init__.py
odoo/addons/beesdoo_stock_coverage/__manifest__.py
odoo/addons/beesdoo_stock_coverage/data/cron.xml
odoo/addons/beesdoo_stock_coverage/models/__init__.py
odoo/addons/beesdoo_stock_coverage/models/product_template.py
odoo/addons/beesdoo_stock_coverage/readme/CONTRIBUTORS.rst
odoo/addons/beesdoo_stock_coverage/readme/DESCRIPTION.rst
odoo/addons/beesdoo_stock_coverage/static/description/index.html
odoo/addons/beesdoo_stock_coverage/tests/__init__.py
odoo/addons/beesdoo_stock_coverage/tests/test_stock_coverage.py
odoo/addons/beesdoo_stock_coverage/views/product_template_view.xml
odoo12_addon_beesdoo_stock_coverage-12.0.0.0.1.99.dev7.dist-info/METADATA
odoo12_addon_beesdoo_stock_coverage-12.0.0.0.1.99.dev7.dist-info/WHEEL
odoo12_addon_beesdoo_stock_coverage-12.0.0.0.1.99.dev7.dist-info/top_level.txt
odoo12_addon_beesdoo_stock_coverage-12.0.0.0.1.99.dev7.dist-info/RECORD
