Metadata-Version: 2.1
Name: odoo12-addon-beesdoo-stock-coverage
Version: 12.0.0.0.1.99.dev7
Summary: Compute estimated stock coverage based on product sales over a date range.
Home-page: https://www.coopiteasy.be
Author: Coop IT Easy SCRLfs
License: AGPL-3
Platform: UNKNOWN
Classifier: Programming Language :: Python
Classifier: Framework :: Odoo
Classifier: License :: OSI Approved :: GNU Affero General Public License v3
Requires-Python: >=3.5
Requires-Dist: odoo (<12.1dev,>=12.0a)
